Metadata-Version: 1.0
Name: jujubigdata
Version: 7.1.0
Summary: Helpers for Juju Charm development for Big Data
Home-page: https://github.com/juju-solutions/jujubigdata
Author: Ubuntu Developers
Author-email: ubuntu-devel-discuss@lists.ubuntu.com
License: Apache License v2.0
Platform: UNKNOWN
